mine/__init__.py
mine/mine.py
napari_picasso/__init__.py
napari_picasso/_widget.py
napari_picasso/main_widget.py
napari_picasso/napari.yaml
napari_picasso/options_widget.py
napari_picasso/sink_widget.py
napari_picasso/source_widget.py
napari_picasso/utils.py
napari_picasso/_tests/__init__.py
napari_picasso/_tests/test_widget.py
picasso/__init__.py
picasso/nn_picasso.py
picasso/picasso.py
picasso/utils.py
picasso/_tests/__init__.py
picasso/_tests/test_picasso.py
napari_PICASSO-0.3.0.dist-info/LICENSE
napari_PICASSO-0.3.0.dist-info/METADATA
napari_PICASSO-0.3.0.dist-info/WHEEL
napari_PICASSO-0.3.0.dist-info/entry_points.txt
napari_PICASSO-0.3.0.dist-info/top_level.txt
napari_PICASSO-0.3.0.dist-info/RECORD
