Metadata-Version: 2.1
Name: napari-PICASSO
Version: 0.3.0
Summary: Blind fluorescence unmixing
Home-page: https://github.com/nygctech/PICASSO
Author: Kunal Pandit
Author-email: kpandit@nygenome.org
License: GPL-3.0-only
Project-URL: Bug Tracker, https://github.com/nygctech/PICASSO/issues
Classifier: Development Status :: 4 - Beta
Classifier: Intended Audience :: Developers
Classifier: Framework :: napari
Classifier: Topic :: Software Development :: Testing
Classifier: Programming Language :: Python
Classifier: Programming Language :: Python :: 3
Classifier: Programming Language :: Python :: 3.8
Classifier: Programming Language :: Python :: 3.9
Classifier: Programming Language :: Python :: 3.10
Classifier: Operating System :: OS Independent
Classifier: License :: OSI Approved :: GNU General Public License v3 (GPLv3)
Requires-Python: >=3.8
License-File: LICENSE
Requires-Dist: numpy
Requires-Dist: magicgui
Requires-Dist: qtpy
Requires-Dist: dask
Requires-Dist: psutil
Provides-Extra: testing
Requires-Dist: tox ; extra == 'testing'
Requires-Dist: napari[all] ; extra == 'testing'
Requires-Dist: torch ; extra == 'testing'
Requires-Dist: pytest ; extra == 'testing'
Requires-Dist: pytest-cov ; extra == 'testing'
Requires-Dist: pytest-qt ; extra == 'testing'
Requires-Dist: xarray ; extra == 'testing'
